raggy/__init__.py
raggy/_version.py
raggy/documents.py
raggy/settings.py
raggy/cli/__init__.py
raggy/loaders/__init__.py
raggy/loaders/base.py
raggy/loaders/github.py
raggy/loaders/pdf.py
raggy/loaders/web.py
raggy/utilities/__init__.py
raggy/utilities/asyncutils.py
raggy/utilities/collections.py
raggy/utilities/embeddings.py
raggy/utilities/filesystem.py
raggy/utilities/ids.py
raggy/utilities/logging.py
raggy/utilities/text.py
raggy/vectorstores/__init__.py
raggy/vectorstores/base.py
raggy/vectorstores/chroma.py
raggy/vectorstores/tpuf.py
raggy-0.3.5.dist-info/METADATA
raggy-0.3.5.dist-info/WHEEL
raggy-0.3.5.dist-info/entry_points.txt
raggy-0.3.5.dist-info/licenses/LICENSE
raggy-0.3.5.dist-info/RECORD
