Metadata-Version: 2.4
Name: raggy
Version: 0.3.5
Summary: scraping stuff
Project-URL: Code, https://github.com/zzstoatzz/raggy
License:                                  Apache License
License-File: LICENSE
Keywords: ai,document-processing,nlp,scraping
Classifier: Programming Language :: Python :: 3 :: Only
Classifier: Programming Language :: Python :: 3.10
Classifier: Programming Language :: Python :: 3.11
Classifier: Programming Language :: Python :: 3.12
Classifier: Topic :: Scientific/Engineering :: Artificial Intelligence
Requires-Python: >=3.10
Requires-Dist: aiofiles
Requires-Dist: bs4
Requires-Dist: chardet
Requires-Dist: fake-useragent
Requires-Dist: gh-util
Requires-Dist: prefect
Requires-Dist: pydantic-ai-slim[openai]
Requires-Dist: pypdf
Requires-Dist: tenacity
Requires-Dist: tiktoken
Requires-Dist: trafilatura
Requires-Dist: typing-extensions
Requires-Dist: xxhash
Requires-Dist: yake
Provides-Extra: chroma
Requires-Dist: chromadb; extra == 'chroma'
Provides-Extra: pdf
Requires-Dist: pypdf; extra == 'pdf'
Provides-Extra: tpuf
Requires-Dist: turbopuffer>=0.6.1; extra == 'tpuf'
